odoo/addons/project_administrator_restricted_visibility/README.rst
odoo/addons/project_administrator_restricted_visibility/__init__.py
odoo/addons/project_administrator_restricted_visibility/__manifest__.py
odoo/addons/project_administrator_restricted_visibility/hooks.py
odoo/addons/project_administrator_restricted_visibility/i18n/it.po
odoo/addons/project_administrator_restricted_visibility/i18n/project_administrator_restricted_visibility.pot
odoo/addons/project_administrator_restricted_visibility/readme/CONFIGURE.md
odoo/addons/project_administrator_restricted_visibility/readme/CONTRIBUTORS.md
odoo/addons/project_administrator_restricted_visibility/readme/DESCRIPTION.md
odoo/addons/project_administrator_restricted_visibility/readme/USAGE.md
odoo/addons/project_administrator_restricted_visibility/security/project_security.xml
odoo/addons/project_administrator_restricted_visibility/static/description/icon.png
odoo/addons/project_administrator_restricted_visibility/static/description/index.html
odoo/addons/project_administrator_restricted_visibility/tests/__init__.py
odoo/addons/project_administrator_restricted_visibility/tests/test_project_administrator_restricted_visibility.py
odoo/addons/project_administrator_restricted_visibility/tests/test_uninstall_hook.py
odoo_addon_project_administrator_restricted_visibility-18.0.1.0.0.2.dist-info/METADATA
odoo_addon_project_administrator_restricted_visibility-18.0.1.0.0.2.dist-info/WHEEL
odoo_addon_project_administrator_restricted_visibility-18.0.1.0.0.2.dist-info/top_level.txt
odoo_addon_project_administrator_restricted_visibility-18.0.1.0.0.2.dist-info/RECORD
